restoring_array_approximate.v
// module mux ();
    
// endmodule

module rhsc (
    input app,
    input x,
    input y,
    output d, bout
);
    assign bout = app ? y : (~x&y);
    assign d = app ? (x|y) : (x^y);
endmodule

module rsc (
    input a,
    input b,
    input bin,
    input appfs,
    output difffs, boutfs
);
    assign boutfs = appfs ? ((~(a&b)&bin)|b) : (bin&(~(a^b))|(~a&b));
    assign difffs = appfs ? (a&b^bin) : (a^b^bin);
endmodule

module ovf (
    output overflow,
    input [3:0] x,
    input [3:0] y
);
   wire [3:0] p;
   wire [3:0] g;
   wire ovf;
   assign p[0] = x[0] | y[0];
   assign p[1] = x[1] | y[1];
   assign p[2] = x[2] | y[2];
   assign p[3] = x[3] | y[3];
   assign g[0] = x[0] & y[0];
   assign g[1] = x[1] & y[1];
   assign g[2] = x[2] & y[2];
   assign g[3] = x[3] & y[3];
   assign ovf = (g[3] | (p[3]&g[2]) | (p[3]&p[2]&g[1]) | (p[3]&p[2]&p[1]&g[0]));
   assign overflow = ~ovf;
endmodule

module array (
    input [7:0] x,
    input [3:0] y,
    input [15:0] a,
    output [3:0] q,
    output [3:0] r
);
    wire o1, o2, o3, o4, o5, o6, o7, o8, o9, o10, o11, o12, o13, o14, o15, o16;
    wire int1, int2, int3, int4, int5, int6, int7, int8, int9, int10, int11, int12, int13, int14, int15, int16;
    wire io1, io2, io3, io4, io5, io6, io7, io8, io9, io10, io11, io12, io13, io14, io15, io16;
    wire iq0, iq1, iq2, iq3;

    rhsc rhsc1 (.x(x[3]), .y(y[0]), .d(io1), .bout(int1), .app(a[0]));
    rsc rsc2 (.a(x[4]), .b(y[1]), .bin(int1), .appfs(a[1]), .difffs(io2), .boutfs(int2));
    rsc rsc3 (.a(x[5]), .b(y[2]), .bin(int2), .appfs(a[2]), .difffs(io3), .boutfs(int3));
    rsc rsc4 (.a(x[6]), .b(y[3]), .bin(int3), .appfs(a[3]), .difffs(io4), .boutfs(int4));
    assign iq3 = x[7] | ~int4;
    assign o1 = iq3 ? io1 : x[3];
    assign o2 = iq3 ? io2 : x[4];
    assign o3 = iq3 ? io3 : x[5];
    assign o4 = iq3 ? io4 : x[6];

    rhsc rhsc5 (.x(x[2]), .y(y[0]), .d(io5), .bout(int5), .app(a[4]));
    rsc rsc6 (.a(o1), .b(y[1]), .bin(int5), .appfs(a[5]), .difffs(io6), .boutfs(int6));
    rsc rsc7 (.a(o2), .b(y[2]), .bin(int6), .appfs(a[6]), .difffs(io7), .boutfs(int7));
    rsc rsc8 (.a(o3), .b(y[3]), .bin(int7), .appfs(a[7]), .difffs(io8), .boutfs(int8));
    assign iq2 = o4 | ~int8;
    assign o5 = iq2 ? io5 : x[3];
    assign o6 = iq2 ? io6 : x[4];
    assign o7 = iq2 ? io7 : x[5];
    assign o8 = iq2 ? io8 : x[6];

    rhsc rhsc9 (.x(x[1]), .y(y[0]), .d(io9), .bout(int9), .app(a[8]));
    rsc rsc10 (.a(o5), .b(y[1]), .bin(int9), .appfs(a[9]), .difffs(io10), .boutfs(int10));
    rsc rsc11 (.a(o6), .b(y[2]), .bin(int10), .appfs(a[10]), .difffs(io11), .boutfs(int11));
    rsc rsc12 (.a(o7), .b(y[3]), .bin(int11), .appfs(a[11]), .difffs(io12), .boutfs(int12));
    assign iq1 = o8 | ~int12;
    assign o9 = iq1 ? io9 : x[3];
    assign o10 = iq1 ? io10 : x[4];
    assign o11 = iq1 ? io11 : x[5];
    assign o12 = iq1 ? io12 : x[6];

    rhsc rhsc13 (.x(x[0]), .y(y[0]), .d(io13), .bout(int13), .app(a[12]));
    rsc rsc14 (.a(o9), .b(y[1]), .bin(int13), .appfs(a[13]), .difffs(io14), .boutfs(int14));
    rsc rsc15 (.a(o10), .b(y[2]), .bin(int14), .appfs(a[14]), .difffs(io15), .boutfs(int15));
    rsc rsc16 (.a(o11), .b(y[3]), .bin(int15), .appfs(a[15]), .difffs(io16), .boutfs(int16));
    assign iq0 = o12 | ~int16;
    assign r[1] = iq0 ? io13 : x[3];
    assign r[1] = iq0 ? io14 : x[4];
    assign r[2] = iq0 ? io15 : x[5];
    assign r[3] = iq0 ? io16 : x[6];

    wire ovf;

    ovf ovf1 (.x(x[7:4]), .y(y), .overflow(ovf));

    assign q[0] = iq0 & ovf;
    assign q[1] = iq1 & ovf;
    assign q[2] = iq2 & ovf;
    assign q[3] = iq3 & ovf;
endmodule

// module ovf_detect();
    
// endmodule

// module restoring_array ();
    
// endmodule

restoring_array_approximate_tb.v
`include "restoring_array_approximate.v"
`timescale 1ns/1ns
module restoring_array_approximate_tb;
    wire [3:0]q;
    wire [3:0]r;
    reg [7:0]x;
    reg [3:0]y;
    reg [15:0]a; // 1000110011101111 ==> approximate mode
    wire d, bout, boutfs, difffs;
    //reg app, x, y, a, b, bin, appfs;
    // reg [3:0] xov;
    // reg [3:0] yov;
    // wire overflow;
    //rhsc u1(.x(x), .y(y), .app(app), .d(d), .bout(bout));
    //rsc u2(.a(a), .b(b), .appfs(appfs), .bin(bin), .difffs(difffs), .boutfs(boutfs));
    array u3(.x(x), .y(y), .q(q), .r(r), .a(a));
    //ovf u3(.x(xov), .y(yov), .overflow(overflow));
    initial begin
        $dumpfile("restoring_array_approximate_tb.vcd");
        $dumpvars(0, restoring_array_approximate_tb);
        a = 0;

        x = 8; y = 4;
        #20;
        x = 7; y = 3;
        #20;
        x = 5; y = 5;
        #20;
        x = 16; y = 4;
        #20
        x = 20; y = 5;
        #20;
        x = 15; y = 3;
        #20;
        x = 12; y = 5;
        #20;
        x = 40; y = 13;
        #20;
        x = 17; y = 5;
        #20;

        a = 36079;
        x = 8; y = 4;
        #20;
        x = 7; y = 3;
        #20;
        x = 5; y = 5;
        #20;
        x = 16; y = 4;
        #20
        x = 20; y = 5;
        #20;
        x = 15; y = 3;
        #20;
        x = 12; y = 5;
        #20;
        x = 40; y = 13;
        #20;
        x = 17; y = 5;
        #20;
    end
endmodule

restoring_array_approximate_tb.vcd
$date
	Wed Jun 30 11:00:46 2021
$end
$version
	Icarus Verilog
$end
$timescale
	1ns
$end
$scope module restoring_array_approximate_tb $end
$var wire 4 ! r [3:0] $end
$var wire 4 " q [3:0] $end
$var reg 16 # a [15:0] $end
$var reg 8 $ x [7:0] $end
$var reg 4 % y [3:0] $end
$scope module u3 $end
$var wire 16 & a [15:0] $end
$var wire 1 ' iq0 $end
$var wire 1 ( iq1 $end
$var wire 1 ) iq2 $end
$var wire 1 * iq3 $end
$var wire 4 + r [3:0] $end
$var wire 8 , x [7:0] $end
$var wire 4 - y [3:0] $end
$var wire 4 . q [3:0] $end
$var wire 1 / ovf $end
$var wire 1 0 o9 $end
$var wire 1 1 o8 $end
$var wire 1 2 o7 $end
$var wire 1 3 o6 $end
$var wire 1 4 o5 $end
$var wire 1 5 o4 $end
$var wire 1 6 o3 $end
$var wire 1 7 o2 $end
$var wire 1 8 o12 $end
$var wire 1 9 o11 $end
$var wire 1 : o10 $end
$var wire 1 ; o1 $end
$var wire 1 < io9 $end
$var wire 1 = io8 $end
$var wire 1 > io7 $end
$var wire 1 ? io6 $end
$var wire 1 @ io5 $end
$var wire 1 A io4 $end
$var wire 1 B io3 $end
$var wire 1 C io2 $end
$var wire 1 D io16 $end
$var wire 1 E io15 $end
$var wire 1 F io14 $end
$var wire 1 G io13 $end
$var wire 1 H io12 $end
$var wire 1 I io11 $end
$var wire 1 J io10 $end
$var wire 1 K io1 $end
$var wire 1 L int9 $end
$var wire 1 M int8 $end
$var wire 1 N int7 $end
$var wire 1 O int6 $end
$var wire 1 P int5 $end
$var wire 1 Q int4 $end
$var wire 1 R int3 $end
$var wire 1 S int2 $end
$var wire 1 T int16 $end
$var wire 1 U int15 $end
$var wire 1 V int14 $end
$var wire 1 W int13 $end
$var wire 1 X int12 $end
$var wire 1 Y int11 $end
$var wire 1 Z int10 $end
$var wire 1 [ int1 $end
$scope module ovf1 $end
$var wire 1 / overflow $end
$var wire 1 \ ovf $end
$var wire 4 ] x [3:0] $end
$var wire 4 ^ y [3:0] $end
$var wire 4 _ p [3:0] $end
$var wire 4 ` g [3:0] $end
$upscope $end
$scope module rhsc1 $end
$var wire 1 a app $end
$var wire 1 b x $end
$var wire 1 c y $end
$var wire 1 K d $end
$var wire 1 [ bout $end
$upscope $end
$scope module rhsc13 $end
$var wire 1 d app $end
$var wire 1 e x $end
$var wire 1 f y $end
$var wire 1 G d $end
$var wire 1 W bout $end
$upscope $end
$scope module rhsc5 $end
$var wire 1 g app $end
$var wire 1 h x $end
$var wire 1 i y $end
$var wire 1 @ d $end
$var wire 1 P bout $end
$upscope $end
$scope module rhsc9 $end
$var wire 1 j app $end
$var wire 1 k x $end
$var wire 1 l y $end
$var wire 1 < d $end
$var wire 1 L bout $end
$upscope $end
$scope module rsc10 $end
$var wire 1 4 a $end
$var wire 1 m appfs $end
$var wire 1 n b $end
$var wire 1 L bin $end
$var wire 1 J difffs $end
$var wire 1 Z boutfs $end
$upscope $end
$scope module rsc11 $end
$var wire 1 3 a $end
$var wire 1 o appfs $end
$var wire 1 p b $end
$var wire 1 Z bin $end
$var wire 1 I difffs $end
$var wire 1 Y boutfs $end
$upscope $end
$scope module rsc12 $end
$var wire 1 2 a $end
$var wire 1 q appfs $end
$var wire 1 r b $end
$var wire 1 Y bin $end
$var wire 1 H difffs $end
$var wire 1 X boutfs $end
$upscope $end
$scope module rsc14 $end
$var wire 1 0 a $end
$var wire 1 s appfs $end
$var wire 1 t b $end
$var wire 1 W bin $end
$var wire 1 F difffs $end
$var wire 1 V boutfs $end
$upscope $end
$scope module rsc15 $end
$var wire 1 : a $end
$var wire 1 u appfs $end
$var wire 1 v b $end
$var wire 1 V bin $end
$var wire 1 E difffs $end
$var wire 1 U boutfs $end
$upscope $end
$scope module rsc16 $end
$var wire 1 9 a $end
$var wire 1 w appfs $end
$var wire 1 x b $end
$var wire 1 U bin $end
$var wire 1 D difffs $end
$var wire 1 T boutfs $end
$upscope $end
$scope module rsc2 $end
$var wire 1 y a $end
$var wire 1 z appfs $end
$var wire 1 { b $end
$var wire 1 [ bin $end
$var wire 1 C difffs $end
$var wire 1 S boutfs $end
$upscope $end
$scope module rsc3 $end
$var wire 1 | a $end
$var wire 1 } appfs $end
$var wire 1 ~ b $end
$var wire 1 S bin $end
$var wire 1 B difffs $end
$var wire 1 R boutfs $end
$upscope $end
$scope module rsc4 $end
$var wire 1 !" a $end
$var wire 1 "" appfs $end
$var wire 1 #" b $end
$var wire 1 R bin $end
$var wire 1 A difffs $end
$var wire 1 Q boutfs $end
$upscope $end
$scope module rsc6 $end
$var wire 1 ; a $end
$var wire 1 $" appfs $end
$var wire 1 %" b $end
$var wire 1 P bin $end
$var wire 1 ? difffs $end
$var wire 1 O boutfs $end
$upscope $end
$scope module rsc7 $end
$var wire 1 7 a $end
$var wire 1 &" appfs $end
$var wire 1 '" b $end
$var wire 1 O bin $end
$var wire 1 > difffs $end
$var wire 1 N boutfs $end
$upscope $end
$scope module rsc8 $end
$var wire 1 6 a $end
$var wire 1 (" appfs $end
$var wire 1 )" b $end
$var wire 1 N bin $end
$var wire 1 = difffs $end
$var wire 1 M boutfs $end
$upscope $end
$upscope $end
$upscope $end
$enddefinitions $end
#0
$dumpvars
0)"
0("
1'"
0&"
0%"
0$"
0#"
0""
0!"
1~
0}
0|
0{
0z
0y
0x
0w
1v
0u
0t
0s
0r
0q
1p
0o
0n
0m
0l
0k
0j
0i
0h
0g
0f
0e
0d
0c
1b
0a
b0 `
b100 _
b100 ^
b0 ]
0\
0[
0Z
1Y
1X
0W
0V
1U
1T
0S
1R
1Q
0P
0O
1N
1M
0L
1K
1J
1I
1H
0G
1F
1E
1D
0C
1B
1A
0@
1?
1>
1=
0<
1;
0:
09
08
07
06
05
14
03
02
01
10
1/
b0 .
b100 -
b1000 ,
b0xz +
0*
0)
0(
0'
b0 &
b100 %
b1000 $
b0 #
b0 "
b0xz !
$end
#20
1?
01
08
06
05
03
02
0:
09
b0 "
b0 .
0*
0)
0(
0'
1Q
1M
1X
1T
1A
1=
1H
1D
1O
1Z
1V
1S
0C
1R
1B
1N
1>
1Y
1I
1U
1E
1[
b11 _
0;
04
00
b0z !
b0z +
1c
1{
0~
1i
1%"
0'"
1l
1n
0p
1f
1t
0v
0b
1h
1k
1e
b11 %
b11 -
b11 ^
b111 $
b111 ,
#40
1S
1C
0B
0O
0?
1>
1Z
1J
0I
0V
0F
1E
1L
1<
b101 _
0{
1~
0%"
1'"
0n
1p
0t
1v
0k
b101 %
b101 -
b101 ^
b101 $
b101 ,
#60
08
09
b101 "
b101 .
1)
0(
1'
0M
1X
0T
1B
0=
1H
0D
0Z
0S
0N
1Y
0U
0J
0>
1I
0E
1C
0[
0K
0L
0<
17
03
1:
b0z !
b0z +
0c
0i
0l
0f
1y
0h
0e
b1 ]
b100 %
b100 -
b100 ^
b10000 $
b10000 ,
#80
b100 "
b100 .
0'
1T
1D
1U
0I
1E
1Z
1V
0C
1J
1F
b0xz !
b0xz +
1[
1K
1L
1<
1W
1G
b1 `
1c
1i
1l
1f
1h
b101 %
b101 -
b101 ^
b10100 $
b10100 ,
#100
1Z
04
1)
03
0?
0T
1'
0D
06
05
0M
01
b101 "
b101 .
09
08
0*
0=
0(
0U
0E
1Q
0N
02
1X
1A
0>
1H
1C
0V
0F
1S
1R
1B
0O
1J
1Y
1I
0[
0L
0W
0K
0<
0G
b0 `
b11 _
1;
07
10
0:
b0z !
b0z +
1{
0~
1%"
0'"
1n
0p
1t
0v
1b
0y
1k
1e
b0 ]
b11 %
b11 -
b11 ^
b1111 $
b1111 ,
#120
08
14
1X
1Y
0)
b0 "
b0 .
0:
09
0'
0(
1H
1M
01
1T
1=
1D
03
02
0S
0C
1B
1?
1N
1>
0Z
0J
1I
0F
1U
1E
1L
1W
b0xz !
b0xz +
1<
1G
b101 _
0{
1~
0%"
1'"
0n
1p
0t
1v
0k
0e
b101 %
b101 -
b101 ^
b1100 $
b1100 ,
#140
0?
0R
1A
0B
1P
1@
b1111 _
16
12
19
b1xz !
b1xz +
1#"
1)"
1r
1x
1|
0h
b10 ]
b1101 %
b1101 -
b1101 ^
b101000 $
b101000 ,
#160
08
0F
01
0(
1'
1M
1X
0T
b1 "
b1 .
0)
1=
1H
0D
05
1O
1Z
1/
0*
1N
1Y
0U
0\
1R
1?
1>
1J
1I
0E
1Q
1A
1[
0C
1B
0W
1K
0G
b1 `
b101 _
0;
17
06
04
13
02
00
1:
09
b0z !
b0z +
0#"
0)"
0r
0x
0b
1y
0|
1e
b1 ]
b101 %
b101 -
b101 ^
b10001 $
b10001 ,
#180
b0 "
b0 .
0'
1T
1D
0O
0Z
1U
b0xz !
b0xz +
0?
1F
1E
0P
0@
0L
0<
b100 _
b0 `
1;
07
14
03
10
0:
0[
0S
0C
0B
0>
0I
0c
0i
0l
0f
1b
0y
0e
b0 ]
1a
1z
1}
1""
1$"
1&"
1("
1o
1q
1w
b100 %
b100 -
b100 ^
b1000 $
b1000 ,
b1000110011101111 #
b1000110011101111 &
#200
03
0?
08
07
06
05
02
01
b0 "
b0 .
0:
09
0'
0*
0)
0(
1I
1T
1Q
1M
1X
1D
1Z
1V
1B
1A
1>
1=
1H
1C
1U
1E
1S
1R
1O
1N
1Y
1[
b11 _
0;
04
00
b0z !
b0z +
1c
1{
0~
1i
1%"
0'"
1l
1n
0p
1f
1t
0v
0b
1h
1k
1e
b11 %
b11 -
b11 ^
b111 $
b111 ,
#220
1I
0>
1Z
1J
0V
0F
1E
1L
0O
1<
b101 _
0{
1~
0%"
1'"
0n
1p
0t
1v
0k
b101 %
b101 -
b101 ^
b101 $
b101 ,
#240
b1 "
b1 .
1'
0T
0D
0B
0Z
0U
0S
0J
1>
1I
0E
0C
0K
0L
0<
0[
17
13
1:
b0z !
b0z +
0c
0i
0l
0f
1y
0h
0e
b1 ]
b100 %
b100 -
b100 ^
b10000 $
b10000 ,
#260
b0 "
b0 .
0'
1T
1D
1U
0I
1E
1B
1Z
1V
1S
1J
1F
1C
b0xz !
b0xz +
1K
1L
1<
1W
1G
1[
b1 `
1c
1i
1l
1f
1h
b101 %
b101 -
b101 ^
b10100 $
b10100 ,
#280
09
1T
1D
0'
02
01
b10 "
b10 .
08
1U
0)
1(
1E
1M
0X
0Z
0J
1V
1F
1=
0H
1?
1>
0I
0L
0W
1O
1N
0Y
0<
0G
b0 `
b11 _
1;
07
14
03
00
0:
b0xz !
b0xz +
1{
0~
1%"
0'"
1n
0p
1t
0v
1b
0y
1k
1e
b0 ]
b11 %
b11 -
b11 ^
b1111 $
b1111 ,
#300
1T
1D
1U
0(
b0 "
b0 .
b0xz !
b0xz +
0'
1X
08
0>
0:
1H
0?
0J
0V
0F
1E
1L
10
1W
0O
1Y
1<
1G
b101 _
0{
1~
0%"
1'"
0n
1p
0t
1v
0k
0e
b101 %
b101 -
b101 ^
b1100 $
b1100 ,
#320
1>
1O
1?
0=
0H
0D
0B
1P
1@
b1111 _
16
12
19
b1xz !
b1xz +
1#"
1)"
1r
1x
1|
0h
b10 ]
b1101 %
b1101 -
b1101 ^
b101000 $
b101000 ,
#340
0F
1Z
1/
01
08
b1 "
b1 .
0U
0\
0)
0(
1'
0>
1J
0I
0E
1=
1H
0D
1B
0W
1M
1X
0T
0G
b1 `
b101 _
0;
17
06
04
13
02
00
1:
09
b0z !
b0z +
0#"
0)"
0r
0x
0b
1y
0|
1e
b1 ]
b101 %
b101 -
b101 ^
b10001 $
b10001 ,
