restoring_array.v
// module restoring_array (
//     input a, b, bin, fbout,  output out, bout
// );
//     wire d;
//     assign d = a ^ b ^ bin;
//     assign bout = (~a) & (b^bin) | (b & bin);
//     assign out = (fbout) ? d : a;
// endmodule

module restoring_array (
    input a, b, bin,  output out, bout
);
    assign out = a ^ b ^ bin;
    assign bout = (~a) & (b^bin) | (b & bin);
endmodule

module array (
    input [7:0]x,
    input [3:0]y,
    input bin1, 
    input bin2,
    input bin3,
    input bin4,
    output [3:0]q, 
    output [3:0]r
);
    wire int1, int2, int3, int4, int5, int6, int7, int8, int9, int10, int11, int12, int13, int14, int15, int16;
    wire o1, o2, o3, o4, o5, o6, o7, o8, o9, o10, o11, o12, o13, o14, o15, o16;
    wire m1, m2, m3, m4, m5, m6, m7, m8, m9, m10, m11, m12;
    
    restoring_array fs1 (.a(x[3]), .b(y[0]), .bin(bin1), .out(o1), .bout(int1));
    restoring_array fs2 (.a(x[4]), .b(y[1]), .bin(int1), .out(o2), .bout(int2));
    restoring_array fs3 (.a(x[5]), .b(y[2]), .bin(int2), .out(o3), .bout(int3));
    restoring_array fs4 (.a(x[6]), .b(y[3]), .bin(int3), .out(o4), .bout(int4));
    assign q[3] = x[7] | ~int4;
    assign m1 = (q[3]) ? o1 : x[3];
    assign m2 = (q[3]) ? o2 : x[4];
    assign m3 = (q[3]) ? o3 : x[5];
    assign m4 = (q[3]) ? o4 : x[6];

    restoring_array fs5 (.a(x[2]), .b(y[0]), .bin(bin2), .out(o5), .bout(int5));
    restoring_array fs6 (.a(m1), .b(y[1]), .bin(int5), .out(o6), .bout(int6));
    restoring_array fs7 (.a(m2), .b(y[2]), .bin(int6), .out(o7), .bout(int7));
    restoring_array fs8 (.a(m3), .b(y[3]), .bin(int7), .out(o8), .bout(int8));
    assign q[2] = m4 | ~int8;
    assign m5 = (q[2]) ? o5 : x[2];
    assign m6 = (q[2]) ? o6 : m1;
    assign m7 = (q[2]) ? o7 : m2;
    assign m8 = (q[2]) ? o8 : m3;

    restoring_array fs9 (.a(x[1]), .b(y[0]), .bin(bin3), .out(o9), .bout(int9));
    restoring_array fs10 (.a(m5), .b(y[1]), .bin(int9), .out(o10), .bout(int10));
    restoring_array fs11 (.a(m6), .b(y[2]), .bin(int10), .out(o11), .bout(int11));
    restoring_array fs12 (.a(m7), .b(y[3]), .bin(int11), .out(o12), .bout(int12));
    assign q[1] = m8 | ~int12;
    assign m9 = (q[1]) ? o9 : x[1];
    assign m10 = (q[1]) ? o10: m5;
    assign m11 = (q[1]) ? o11 : m6;
    assign m12 = (q[1]) ? o12 : m7;

    restoring_array fs13 (.a(x[0]), .b(y[0]), .bin(bin4), .out(o13), .bout(int13));
    restoring_array fs14 (.a(m9), .b(y[1]), .bin(int13), .out(o14), .bout(int14));
    restoring_array fs15 (.a(m10), .b(y[2]), .bin(int14), .out(o15), .bout(int15));
    restoring_array fs16 (.a(m11), .b(y[3]), .bin(int15), .out(o16), .bout(int16));
    assign q[0] = m12 | ~int16;
    assign r[0] = (q[0]) ? o13 : x[0];
    assign r[1] = (q[0]) ? o14 : m9;
    assign r[2] = (q[0]) ? o15 : m10;
    assign r[3] = (q[0]) ? o16 : m11;

endmodule

restoring_array_tb.v
`include "restoring_array.v"
`timescale 1ns/1ns
module restoring_array_tb;
    wire [3:0]q;
    wire [3:0]r;
    reg [7:0]x;
    reg [3:0]y;
    reg bin1;
    reg bin2;
    reg bin3;
    reg bin4;
    array div (.x(x), .y(y), .bin1(bin1), .bin2(bin2), .bin3(bin3), .bin4(bin4), .q(q), .r(r));
    initial begin
        $dumpfile("restoring_array_tb.vcd");
        $dumpvars(0, restoring_array_tb);
        bin1 = 0; bin2 = 0; bin3 = 0; bin4 = 0;
        x = 8; y = 4;
        #20;
        x = 7; y = 3;
        #20;
        x = 5; y = 5;
        #20;
        x = 16; y = 4;
        #20
        x = 20; y = 5;
        #20;
        x = 15; y = 3;
        #20;
        x = 12; y = 5;
        #20;
        x = 40; y = 13;
        #20;
        x = 17; y = 5;
        #20;
    end
endmodule

restoring_array_tb.vcd
$date
	Fri May 21 20:18:22 2021
$end
$version
	Icarus Verilog
$end
$timescale
	1ns
$end
$scope module restoring_array_tb $end
$var wire 4 ! r [3:0] $end
$var wire 4 " q [3:0] $end
$var reg 1 # bin1 $end
$var reg 1 $ bin2 $end
$var reg 1 % bin3 $end
$var reg 1 & bin4 $end
$var reg 8 ' x [7:0] $end
$var reg 4 ( y [3:0] $end
$scope module div $end
$var wire 1 # bin1 $end
$var wire 1 $ bin2 $end
$var wire 1 % bin3 $end
$var wire 1 & bin4 $end
$var wire 8 ) x [7:0] $end
$var wire 4 * y [3:0] $end
$var wire 4 + r [3:0] $end
$var wire 4 , q [3:0] $end
$var wire 1 - o9 $end
$var wire 1 . o8 $end
$var wire 1 / o7 $end
$var wire 1 0 o6 $end
$var wire 1 1 o5 $end
$var wire 1 2 o4 $end
$var wire 1 3 o3 $end
$var wire 1 4 o2 $end
$var wire 1 5 o16 $end
$var wire 1 6 o15 $end
$var wire 1 7 o14 $end
$var wire 1 8 o13 $end
$var wire 1 9 o12 $end
$var wire 1 : o11 $end
$var wire 1 ; o10 $end
$var wire 1 < o1 $end
$var wire 1 = m9 $end
$var wire 1 > m8 $end
$var wire 1 ? m7 $end
$var wire 1 @ m6 $end
$var wire 1 A m5 $end
$var wire 1 B m4 $end
$var wire 1 C m3 $end
$var wire 1 D m2 $end
$var wire 1 E m12 $end
$var wire 1 F m11 $end
$var wire 1 G m10 $end
$var wire 1 H m1 $end
$var wire 1 I int9 $end
$var wire 1 J int8 $end
$var wire 1 K int7 $end
$var wire 1 L int6 $end
$var wire 1 M int5 $end
$var wire 1 N int4 $end
$var wire 1 O int3 $end
$var wire 1 P int2 $end
$var wire 1 Q int16 $end
$var wire 1 R int15 $end
$var wire 1 S int14 $end
$var wire 1 T int13 $end
$var wire 1 U int12 $end
$var wire 1 V int11 $end
$var wire 1 W int10 $end
$var wire 1 X int1 $end
$scope module fs1 $end
$var wire 1 Y a $end
$var wire 1 Z b $end
$var wire 1 # bin $end
$var wire 1 X bout $end
$var wire 1 < out $end
$upscope $end
$scope module fs10 $end
$var wire 1 A a $end
$var wire 1 [ b $end
$var wire 1 W bout $end
$var wire 1 ; out $end
$var wire 1 I bin $end
$upscope $end
$scope module fs11 $end
$var wire 1 @ a $end
$var wire 1 \ b $end
$var wire 1 W bin $end
$var wire 1 V bout $end
$var wire 1 : out $end
$upscope $end
$scope module fs12 $end
$var wire 1 ? a $end
$var wire 1 ] b $end
$var wire 1 V bin $end
$var wire 1 U bout $end
$var wire 1 9 out $end
$upscope $end
$scope module fs13 $end
$var wire 1 ^ a $end
$var wire 1 _ b $end
$var wire 1 & bin $end
$var wire 1 T bout $end
$var wire 1 8 out $end
$upscope $end
$scope module fs14 $end
$var wire 1 = a $end
$var wire 1 ` b $end
$var wire 1 T bin $end
$var wire 1 S bout $end
$var wire 1 7 out $end
$upscope $end
$scope module fs15 $end
$var wire 1 G a $end
$var wire 1 a b $end
$var wire 1 S bin $end
$var wire 1 R bout $end
$var wire 1 6 out $end
$upscope $end
$scope module fs16 $end
$var wire 1 F a $end
$var wire 1 b b $end
$var wire 1 R bin $end
$var wire 1 Q bout $end
$var wire 1 5 out $end
$upscope $end
$scope module fs2 $end
$var wire 1 c a $end
$var wire 1 d b $end
$var wire 1 X bin $end
$var wire 1 P bout $end
$var wire 1 4 out $end
$upscope $end
$scope module fs3 $end
$var wire 1 e a $end
$var wire 1 f b $end
$var wire 1 P bin $end
$var wire 1 O bout $end
$var wire 1 3 out $end
$upscope $end
$scope module fs4 $end
$var wire 1 g a $end
$var wire 1 h b $end
$var wire 1 O bin $end
$var wire 1 N bout $end
$var wire 1 2 out $end
$upscope $end
$scope module fs5 $end
$var wire 1 i a $end
$var wire 1 j b $end
$var wire 1 $ bin $end
$var wire 1 M bout $end
$var wire 1 1 out $end
$upscope $end
$scope module fs6 $end
$var wire 1 H a $end
$var wire 1 k b $end
$var wire 1 M bin $end
$var wire 1 L bout $end
$var wire 1 0 out $end
$upscope $end
$scope module fs7 $end
$var wire 1 D a $end
$var wire 1 l b $end
$var wire 1 L bin $end
$var wire 1 K bout $end
$var wire 1 / out $end
$upscope $end
$scope module fs8 $end
$var wire 1 C a $end
$var wire 1 m b $end
$var wire 1 K bin $end
$var wire 1 J bout $end
$var wire 1 . out $end
$upscope $end
$scope module fs9 $end
$var wire 1 n a $end
$var wire 1 o b $end
$var wire 1 % bin $end
$var wire 1 I bout $end
$var wire 1 - out $end
$upscope $end
$upscope $end
$upscope $end
$enddefinitions $end
#0
$dumpvars
0o
0n
0m
1l
0k
0j
0i
0h
0g
1f
0e
0d
0c
0b
1a
0`
0_
0^
0]
1\
0[
0Z
1Y
0X
0W
0V
0U
0T
0S
1R
1Q
0P
1O
1N
0M
0L
1K
1J
0I
1H
0G
0F
0E
0D
0C
0B
0A
1@
0?
0>
0=
1<
0;
0:
09
08
07
16
15
04
13
12
01
10
1/
1.
0-
b10 ,
b0 +
b100 *
b1000 )
b100 (
b1000 '
0&
0%
0$
0#
b10 "
b0 !
$end
#20
0=
0U
0V
0E
0G
0W
10
09
0;
0B
0C
0>
0?
b10 "
b10 ,
1N
1J
1Q
12
1.
15
1P
1O
1L
1K
0F
1S
1R
1X
04
13
1/
0:
17
16
0@
0H
1A
b1 !
b1 +
1Z
1d
0f
1j
1k
0l
1o
1[
0\
1_
1`
0a
0Y
1i
1n
1^
b11 (
b11 *
b111 '
b111 )
#40
0W
0@
0>
0?
1A
0B
0D
0H
05
1J
1N
1.
0Q
b1 "
b1 ,
1U
12
1K
0E
0R
1O
19
b0 !
b0 +
0L
1G
0F
1V
0S
0=
1I
14
1P
03
00
1/
0;
1:
07
06
1-
0d
1f
0k
1l
0[
1\
0`
1a
0n
b101 (
b101 *
b101 '
b101 )
#60
0>
0B
0C
0F
1V
1N
1Q
b100 "
b100 ,
0J
12
15
1O
1U
0.
b0 !
b0 +
1R
1:
13
19
0K
16
0W
0X
0I
0P
0E
0/
0;
0<
0-
14
0?
0G
1D
0A
0Z
0j
0o
0_
1c
0i
0^
b100 (
b100 *
b10000 '
b10000 )
#80
0:
06
1W
1S
04
1;
17
1X
1I
1T
1<
1-
18
1Z
1j
1o
1_
1i
b101 (
b101 *
b10100 '
b10100 )
#100
1W
0A
0J
0K
0>
0?
0@
0L
0.
0/
00
0B
0C
0E
0F
0G
b101 "
b101 ,
1N
1U
0Q
0S
12
14
07
1O
19
05
0X
0I
0T
1P
13
1;
1:
1V
06
0R
0<
0-
08
1H
0D
1=
b0 !
b0 +
1d
0f
1k
0l
1[
0\
1`
0a
1Y
0c
1n
1^
b11 (
b11 *
b1111 '
b1111 )
#120
0B
0C
1H
1A
09
1N
0G
12
0U
b10 "
b10 ,
1J
1Q
0S
1O
0>
0V
0F
0E
1.
15
07
0P
1@
0?
1K
0W
1R
1I
b10 !
b10 +
1T
04
13
10
1/
0;
0:
16
1-
18
1=
0d
1f
0k
1l
0[
1\
0`
1a
0n
0^
b101 (
b101 *
b1100 '
b1100 )
#140
1J
0S
07
1K
1=
1/
0?
0L
1.
1@
0B
1H
0Q
0R
06
1F
1V
1N
b1 !
b1 +
1:
b11 "
b11 ,
00
1G
1W
0E
1U
0O
1M
1;
12
09
05
03
1>
11
1C
0A
1h
1m
1]
1b
1e
0i
b1101 (
b1101 *
b101000 '
b101000 )
#160
0Q
1V
1W
1;
0R
0B
06
0A
1.
0F
1G
1=
0:
1L
1K
17
1N
0E
1X
1O
10
1/
b11 "
b11 ,
b10 !
b10 +
0T
12
1J
09
0U
05
1<
04
13
0@
1?
0>
08
0H
1D
0C
0h
0m
0]
0b
0Y
1c
0e
1^
b101 (
b101 *
b10001 '
b10001 )
